ezface/__init__.py
ezface/ezface_package.py
hah/__init__.py
hah/ezface_package.py
get_hahaha-0.0.1.dist-info/METADATA
get_hahaha-0.0.1.dist-info/WHEEL
get_hahaha-0.0.1.dist-info/top_level.txt
get_hahaha-0.0.1.dist-info/RECORD
