Metadata-Version: 2.1
Name: get-hahaha
Version: 0.0.1
Summary: This project provides an easy way to recognize faces usingAI
Home-page: https://www.baidu.com
Author: fan_chengfeng
Author-email: 2737693820@qq.com
